<?xml version='1.1' encoding='UTF-8'?>
<com.cloudbees.plugins.credentials.SystemCredentialsProvider plugin="credentials@1189.vf61b_a_5e2f62e">
  <domainCredentialsMap class="hudson.util.CopyOnWriteMap$Hash">
    <entry>
      <com.cloudbees.plugins.credentials.domains.Domain>
        <specifications/>
      </com.cloudbees.plugins.credentials.domains.Domain>
      <java.util.concurrent.CopyOnWriteArrayList>
        <org.jenkinsci.plugins.plaincredentials.impl.StringCredentialsImpl plugin="plain-credentials@139.ved2b_9cf7587b">
          <scope>GLOBAL</scope>
          <id>77f2c967-90ea-4716-966b-e312ba8b3527</id>
          <description></description>
          <secret>{AQAAABAAAAAwp9aiTcHcRQXol+vz8CMho3wcdKggR9WALd9pHXBjOTMnLO8NL5gcEc4nwDqk2xC9HW3zlYzJzK7JlJsQ89OW6Q==}</secret>
        </org.jenkinsci.plugins.plaincredentials.impl.StringCredentialsImpl>
      </java.util.concurrent.CopyOnWriteArrayList>
    </entry>
  </domainCredentialsMap>
</com.cloudbees.plugins.credentials.SystemCredentialsProvider>